gcp_platforms_auto/__init__.py
gcp_platforms_auto/git.py
gcp_platforms_auto-0.6.5.dist-info/METADATA
gcp_platforms_auto-0.6.5.dist-info/WHEEL
gcp_platforms_auto-0.6.5.dist-info/top_level.txt
gcp_platforms_auto-0.6.5.dist-info/RECORD
