Metadata-Version: 2.4
Name: gcp_platforms_auto
Version: 0.6.5
Summary: A brief description of your package
Author-email: ofir4858 <ofirshasha10@gmail.com>
License: MIT
Classifier: Programming Language :: Python :: 3
Classifier: License :: OSI Approved :: MIT License
Classifier: Operating System :: OS Independent
Requires-Python: >=3.6
Requires-Dist: requests
Requires-Dist: pyjwt
Requires-Dist: google-cloud-logging
Requires-Dist: gitpython
